{
  "frames": [
    {
      "filename": "walk001",
      "frame": { "x": 16, "y": 0, "w": 15, "h": 20 },
      "rotated": false,
      "trimmed": false,
      "spriteSourceSize": { "x": 0, "y": 0, "w": 15, "h": 20 },
      "sourceSize": { "w": 15, "h": 20 }
    },
    {
      "filename": "walk002",
      "frame": { "x": 0, "y": 21, "w": 15, "h": 21 },
      "rotated": false,
      "trimmed": false,
      "spriteSourceSize": { "x": 0, "y": 0, "w": 15, "h": 21 },
      "sourceSize": { "w": 15, "h": 21 }
    },
    {
      "filename": "walk004",
      "frame": { "x": 48, "y": 0, "w": 15, "h": 22 },
      "rotated": false,
      "trimmed": false,
      "spriteSourceSize": { "x": 0, "y": 0, "w": 15, "h": 22 },
      "sourceSize": { "w": 15, "h": 22 }
    },
    {
      "filename": "walk000",
      "frame": { "x": 0, "y": 0, "w": 15, "h": 20 },
      "rotated": false,
      "trimmed": false,
      "spriteSourceSize": { "x": 0, "y": 0, "w": 15, "h": 20 },
      "sourceSize": { "w": 15, "h": 20 }
    },
    {
      "filename": "stand000",
      "frame": { "x": 32, "y": 21, "w": 15, "h": 20 },
      "rotated": false,
      "trimmed": false,
      "spriteSourceSize": { "x": 0, "y": 0, "w": 15, "h": 20 },
      "sourceSize": { "w": 15, "h": 20 }
    },
    {
      "filename": "stand001",
      "frame": { "x": 32, "y": 0, "w": 15, "h": 20 },
      "rotated": false,
      "trimmed": false,
      "spriteSourceSize": { "x": 0, "y": 0, "w": 15, "h": 20 },
      "sourceSize": { "w": 15, "h": 20 }
    },
    {
      "filename": "stand002",
      "frame": { "x": 16, "y": 21, "w": 15, "h": 20 },
      "rotated": false,
      "trimmed": false,
      "spriteSourceSize": { "x": 0, "y": 0, "w": 15, "h": 20 },
      "sourceSize": { "w": 15, "h": 20 }
    },
    {
      "filename": "stand003",
      "frame": { "x": 48, "y": 23, "w": 15, "h": 19 },
      "rotated": false,
      "trimmed": false,
      "spriteSourceSize": { "x": 0, "y": 0, "w": 15, "h": 19 },
      "sourceSize": { "w": 15, "h": 19 }
    }
  ],
  "meta": {
    "app": "https://www.leshylabs.com/apps/sstool/",
    "version": "Leshy SpriteSheet Tool v0.8.4",
    "image": "spritesheet.png",
    "size": { "w": 63, "h": 42 },
    "scale": 1
  }
}
